infini-2.1.15.dist-info/METADATA
infini-2.1.15.dist-info/WHEEL
infini-2.1.15.dist-info/licenses/LICENSE
infini/__init__.py
infini/core.py
infini/doc.py
infini/exceptions.py
infini/generator.py
infini/handler.py
infini/injector.py
infini/input.py
infini/interceptor.py
infini/internal.py
infini/loader.py
infini/logging.py
infini/output.py
infini/queue.py
infini/register.py
infini/router.py
infini/typing.py
infini-2.1.15.dist-info/RECORD
