Metadata-Version: 2.1
Name: infini
Version: 2.1.15
Summary: Infini 内容输入输出流框架
Author-Email: 苏向夜 <fu050409@163.com>, 简律纯 <leader@hydroroll.team>
License: MIT
Project-URL: Homepage, https://grps.hydroroll.team
Project-URL: Documentation, https://grps.hydroroll.team
Project-URL: Repository, https://github.com/HydroRoll-Team/infini
Project-URL: Changelog, https://infini.hydroroll.team/zh_CN/latest/changelog.html
Requires-Python: >=3.8
Requires-Dist: rich>=13.7.0
Requires-Dist: jinja2>=3.1.3
